WorkWeixinRobot/__init__.py
WorkWeixinRobot/work_weixin_robot.py
WorkWeixinRobot-1.0.1.dist-info/LICENSE
WorkWeixinRobot-1.0.1.dist-info/METADATA
WorkWeixinRobot-1.0.1.dist-info/WHEEL
WorkWeixinRobot-1.0.1.dist-info/entry_points.txt
WorkWeixinRobot-1.0.1.dist-info/top_level.txt
WorkWeixinRobot-1.0.1.dist-info/RECORD
