Metadata-Version: 2.1
Name: WorkWeixinRobot
Version: 1.0.1
Summary: 企业微信群机器人
Home-page: https://github.com/seoktaehyeon/work-weixin-robot
Author: Will
Author-email: v.stone@163.com
Maintainer: Will
Maintainer-email: v.stone@163.com
License: MIT
Platform: any
Requires-Dist: requests
Requires-Dist: PyYAML
